argsimple/__init__.py
argsimple/cli.py
argsimple/exception.py
argsimple/help.py
argsimple/option.py
argsimple-0.1.0.dist-info/LICENSE
argsimple-0.1.0.dist-info/METADATA
argsimple-0.1.0.dist-info/WHEEL
argsimple-0.1.0.dist-info/top_level.txt
argsimple-0.1.0.dist-info/RECORD
